pythonsl/__init__.py
pythonsl-0.0.1.dist-info/LICENSE
pythonsl-0.0.1.dist-info/METADATA
pythonsl-0.0.1.dist-info/WHEEL
pythonsl-0.0.1.dist-info/top_level.txt
pythonsl-0.0.1.dist-info/RECORD
