Metadata-Version: 2.1
Name: pythonsl
Version: 0.0.1
Summary: A python client for running tests in sauce labs
Home-page: https://github.com/rohanj-qxf2/pythonsl
Author: Rohan Joshi
Author-email: rohan.j@qxf2.com
License: UNKNOWN
Platform: UNKNOWN
Classifier: Programming Language :: Python :: 3
Classifier: License :: OSI Approved :: MIT License
Classifier: Operating System :: OS Independent
